Metadata-Version: 1.1
Name: cophi-toolbox
Version: 0.1.1.dev0
Summary: Computer Philology Toolbox
Home-page: UNKNOWN
Author: DARIAH-DE Wuerzburg Group
Author-email: pielstroem@biozentrum.uni-wuerzburg.de
License: UNKNOWN
Platform: UNKNOWN
Classifier: Development Status :: 3 - Alpha
Classifier: Programming Language :: Python :: 3.4
Classifier: Programming Language :: Python :: 3.5
Classifier: Programming Language :: Python :: 3.6
